COPYING
COPYING.LESSER
MANIFEST.in
NEWS
README
setup.cfg
setup.py
docs/api-collections.rst
docs/api-exceptions.rst
docs/api-i18n.rst
docs/api-iterutils.rst
docs/api-overview.rst
docs/api-pycompat24.rst
docs/api-pycompat25.rst
docs/api-pycompat27.rst
docs/api-text-converters.rst
docs/api-text-display.rst
docs/api-text-misc.rst
docs/api-text-utf8.rst
docs/api-text.rst
docs/api-versioning.rst
docs/conf.py
docs/designing-unicode-apis.rst
docs/glossary.rst
docs/hacking.rst
docs/index.rst
docs/porting-guide-0.3.rst
docs/tutorial.rst
docs/unicode-frustrations.rst
kitchen/__init__.py
kitchen/exceptions.py
kitchen/release.py
kitchen.egg-info/PKG-INFO
kitchen.egg-info/SOURCES.txt
kitchen.egg-info/dependency_links.txt
kitchen.egg-info/top_level.txt
kitchen/collections/__init__.py
kitchen/collections/strictdict.py
kitchen/i18n/__init__.py
kitchen/iterutils/__init__.py
kitchen/pycompat24/__init__.py
kitchen/pycompat24/subprocess.py
kitchen/pycompat24/base64/__init__.py
kitchen/pycompat24/base64/_base64.py
kitchen/pycompat24/sets/__init__.py
kitchen/pycompat25/__init__.py
kitchen/pycompat25/collections/__init__.py
kitchen/pycompat25/collections/_defaultdict.py
kitchen/pycompat27/__init__.py
kitchen/pycompat27/subprocess/__init__.py
kitchen/pycompat27/subprocess/_subprocess.py
kitchen/text/__init__.py
kitchen/text/converters.py
kitchen/text/display.py
kitchen/text/exceptions.py
kitchen/text/misc.py
kitchen/text/utf8.py
kitchen/versioning/__init__.py
tests/base_classes.py
tests/test__all__.py
tests/test_base64.py
tests/test_collections.py
tests/test_converters.py
tests/test_defaultdict.py
tests/test_deprecation.py
tests/test_i18n.py
tests/test_iterutils.py
tests/test_pycompat.py
tests/test_pycompat24.py
tests/test_subprocess.py
tests/test_text_display.py
tests/test_text_misc.py
tests/test_text_utf8.py
tests/test_versioning.py
tests/data/locale/pt_BR.po
tests/data/locale/test.pot
tests/data/locale/pt_BR/LC_MESSAGES/test.mo