Metadata-Version: 1.0
Name: kitchen
Version: 0.2.4
Summary: Kitchen contains a cornucopia of useful code
Home-page: https://fedorahosted.org/kitchen
Author: Toshio Kuratomi
Author-email: toshio@fedoraproject.org
License: LGPLv2+
Download-URL: https://fedorahosted.org/releases/k/i/kitchen
Keywords: Useful Small Code Snippets
Platform: UNKNOWN
Classifier: Development Status :: 4 - Beta
Classifier: License :: OSI Approved :: GNU Library or Lesser General Public License (LGPL)
Classifier: Operating System :: OS Independent
Classifier: Programming Language :: Python :: 2.3
Classifier: Programming Language :: Python :: 2.4
Classifier: Programming Language :: Python :: 2.5
Classifier: Programming Language :: Python :: 2.6
Classifier: Programming Language :: Python :: 2.7
Classifier: Topic :: Software Development :: Internationalization
Classifier: Topic :: Software Development :: Libraries :: Python Modules
Classifier: Topic :: Text Processing :: General
